disbase/__init__.py
disbase/_info.py
disbase/app/__init__.py
disbase/app/gateway.py
disbase/app/rest.py
disbase/assets.py
disbase/errors.py
disbase/file.py
disbase/flags.py
disbase/guild.py
disbase/internal/__init__.py
disbase/internal/blocks.py
disbase/internal/events.py
disbase/internal/gateway/__init__.py
disbase/internal/gateway/cluster.py
disbase/internal/gateway/manager.py
disbase/internal/gateway/shard.py
disbase/internal/http/__init__.py
disbase/internal/http/emoji.py
disbase/internal/http/guild.py
disbase/internal/http/route.py
disbase/internal/logs.py
disbase/mixins.py
disbase/mod/__init__.py
disbase/mod/extensions.py
disbase/state.py
disbase/types.py
disbase/user.py
disbase/utils.py
disbase-0.1.0.dist-info/LICENSE
disbase-0.1.0.dist-info/WHEEL
disbase-0.1.0.dist-info/METADATA
disbase-0.1.0.dist-info/RECORD
